Metadata-Version: 2.1
Name: oort-cloud
Version: 1.13.1
Summary: Oort utility to upload all your files in Arcsecond.io's cloud storage.
Home-page: https://github.com/arcsecond-io/oort
Author: Cedric Foellmi
Author-email: cedric@arcsecond.io
License: MIT
Platform: any
Classifier: Development Status :: 5 - Production/Stable
Classifier: Environment :: Console
Classifier: Intended Audience :: Science/Research
Classifier: License :: OSI Approved :: MIT License
Classifier: Operating System :: POSIX
Classifier: Operating System :: MacOS
Classifier: Operating System :: Unix
Classifier: Operating System :: Microsoft :: Windows
Classifier: Programming Language :: Python
Classifier: Programming Language :: Python :: 3
Classifier: Programming Language :: Python :: 3.7
Classifier: Programming Language :: Python :: 3.8
Classifier: Programming Language :: Python :: 3.9
Classifier: Topic :: Software Development :: Libraries :: Python Modules
License-File: LICENSE
Requires-Dist: arcsecond >=2.0.4
Requires-Dist: astropy >=5
Requires-Dist: flask >=2.2
Requires-Dist: peewee >=3
Requires-Dist: watchdog >=2.2
Requires-Dist: supervisor >4.2.2
Requires-Dist: dateparser
Requires-Dist: python-dotenv
